quick_data_clean/LICENSE_OPENSSL.txt
quick_data_clean/__init__.py
quick_data_clean/asymmetric_algo.dll
quick_data_clean/libeay32.dll
quick_data_clean/quick_algo.py
quick_data_clean/quick_algo_asymmetric.py
quick_data_clean/quick_common.py
quick_data_clean/quick_db.py
quick_data_clean/quick_excel.py
quick_data_clean/quick_file.py
quick_data_clean/quick_gui.py
quick_data_clean/test.py
quick_data_clean-1.1.18.dist-info/METADATA
quick_data_clean-1.1.18.dist-info/WHEEL
quick_data_clean-1.1.18.dist-info/top_level.txt
quick_data_clean-1.1.18.dist-info/RECORD
